vap_mcp/__init__.py
vap_mcp/__main__.py
vap_mcp/server.py
vap_mcp-0.2.1.dist-info/METADATA
vap_mcp-0.2.1.dist-info/WHEEL
vap_mcp-0.2.1.dist-info/entry_points.txt
vap_mcp-0.2.1.dist-info/licenses/LICENSE
vap_mcp-0.2.1.dist-info/RECORD
