Metadata-Version: 2.4
Name: vap-mcp
Version: 0.2.1
Summary: VAP MCP Server - Execution control layer for Claude Desktop and MCP clients
Project-URL: Homepage, https://vapagent.com
Project-URL: Documentation, https://api.vapagent.com/docs
Project-URL: Repository, https://github.com/elestirelbilinc-sketch/vap-showcase
Project-URL: MCP_Registry, https://registry.modelcontextprotocol.io
Author-email: VAP Team <support@vapagent.com>
License-Expression: MIT
License-File: LICENSE
Keywords: ai-agents,claude,claude-desktop,cost-control,execution-control,mcp,vap,vapagent
Classifier: Development Status :: 4 - Beta
Classifier: Intended Audience :: Developers
Classifier: License :: OSI Approved :: MIT License
Classifier: Programming Language :: Python :: 3
Classifier: Programming Language :: Python :: 3.10
Classifier: Programming Language :: Python :: 3.11
Classifier: Programming Language :: Python :: 3.12
Classifier: Topic :: Multimedia :: Graphics
Classifier: Topic :: Multimedia :: Sound/Audio
Classifier: Topic :: Multimedia :: Video
Classifier: Topic :: Scientific/Engineering :: Artificial Intelligence
Requires-Python: >=3.10
Requires-Dist: httpx>=0.25.0
Requires-Dist: mcp>=1.0.0
